{
  "_version": 2,
  "users": {
    "89292839878717@s.whatsapp.net": {
      "id": "89292839878717@s.whatsapp.net",
      "nickname": "",
      "ggc": 100,
      "bank": 0,
      "level": 1,
      "xp": 0,
      "hp": 100,
      "maxHp": 100,
      "class": "none",
      "inventory": {},
      "fish": {},
      "daily": {
        "last": 0,
        "streak": 0
      },
      "work": {
        "last": 0
      },
      "stats": {
        "fishCaught": 0,
        "moneyEarned": 0,
        "commandsUsed": 0
      }
    }
  }
}